[{"productID":"13f6fa67-2cdb-4823-b4dd-52d94e373782","ownerID":"94115dfd-f3e3-4c20-b620-199e5cf6cbbc","name":"test 502","description":"test 502 test 502 test 502 test 502 test 502","price":"500","category":"Electronics","sold":0,"deleted":0,"condition":"New","delivery":"Public meetup","created_at":"2026-05-01 12:35:18","imageCount":1,"subcategory":"","views":null,"latitude":-33.96,"longitude":25.52,"distance":0.00013425878593145295,"primaryImage":"13f6fa67-2cdb-4823-b4dd-52d94e373782_a.webp"},{"productID":"550e8400-e29b-41d4-a716-100000000007","ownerID":"a1f5c9f0-9b3d-4d87-8b2d-000000000007","name":"Digital Camera","description":"Capture high quality photos","price":"300","category":"electronics","sold":0,"deleted":0,"condition":"New","delivery":null,"created_at":"2026-03-23 12:00:56","imageCount":1,"subcategory":"","views":null,"latitude":-33.96,"longitude":25.52,"distance":0.00013425878593145295,"primaryImage":null},{"productID":"550e8400-e29b-41d4-a716-100000000010","ownerID":"a1f5c9f0-9b3d-4d87-8b2d-000000000010","name":"Drone","description":"Quadcopter with camera","price":"200","category":"electronics","sold":0,"deleted":0,"condition":"New","delivery":null,"created_at":"2026-03-23 12:00:56","imageCount":1,"subcategory":"","views":null,"latitude":-33.96,"longitude":25.52,"distance":0.00013425878593145295,"primaryImage":null},{"productID":"550e8400-e29b-41d4-a716-100000000024","ownerID":"a1f5c9f0-9b3d-4d87-8b2d-000000000024","name":"Lawn Mower","description":"Electric push lawn mower","price":"250","category":"garden equipment","sold":0,"deleted":0,"condition":"New","delivery":null,"created_at":"2026-03-23 12:00:56","imageCount":1,"subcategory":"","views":null,"latitude":-33.96,"longitude":25.52,"distance":0.00013425878593145295,"primaryImage":null},{"productID":"550e8400-e29b-41d4-a716-100000000027","ownerID":"a1f5c9f0-9b3d-4d87-8b2d-000000000027","name":"VR Headset","description":"Virtual reality headset","price":"300","category":"electronics","sold":0,"deleted":0,"condition":"New","delivery":null,"created_at":"2026-03-23 12:00:56","imageCount":1,"subcategory":"","views":null,"latitude":-33.96,"longitude":25.52,"distance":0.00013425878593145295,"primaryImage":null},{"productID":"f24a120d-6375-4421-b799-3c165e11ed53","ownerID":"a1f5c9f0-9b3d-4d87-8b2d-000000000001","name":"test_item_24","description":"test_item_24 test_item_24 test_item_24 test_item_24test_item_24 test_item_24 test_item_24 test_item_24 test_item_24 test_item_24test_item_24 test_item_24 test_item_24 test_item_24 test_item_24\r\ntest_item_24\r\ntest_item_24\r\ntest_item_24 test_item_24","price":"234","category":"Bedding","sold":0,"deleted":0,"condition":"Broken","delivery":"Door pick-up","created_at":"2026-04-10 10:40:12","imageCount":1,"subcategory":"","views":null,"latitude":-33.96,"longitude":25.52,"distance":0.00013425878593145295,"primaryImage":null}]